Workbook

Sheet Read Me
A1: Read Me - How This Workbook Is Organized
A3: Executive Summary | C3: Start here. The one-line takeaway, a confidence-tiered list of findings (high / moderate / low), key stat tiles, and a map of the rest of the workbook.
A4: YoY Fundamentals | C4: The core deliverable you asked for: one row per midterm-election year (1962-2026) with the macro catalyst, a plain-language 'what happened' narrative, and the SPX/DJI/Nasdaq reaction.
A5: The N-Pattern Visualized | C5: The averaged price-path chart the 'N' idea comes from, with phase-by-phase annotation, plus a chart showing how often a true N actually occurs versus the more common 'higher low, no retest' outcome.
A6: Probability Scorecard | C6: Every observation (rally into the election, retest odds, 6/12-month odds, etc.) as a live, color-coded hit rate, recalculated with COUNTIF/COUNTIFS formulas straight from the data tabs.
A7: Hypothesis Tests | C7: Four formal statistical tests: (1) is the average 6-month return different from zero, (2) is 'up 6 months later' better than a coin flip, (3) does the pre-election rally size predict the 6-month return, (4) does the depth of the post-election dip predict the 6-month rebound.
A8: Midterm Cycle Effect | C8: Puts midterm years in context against the other three years of the 4-year presidential cycle - this is the well-documented 'midterm effect' and the main reason the 6-month odds are so good.
A9: Data - SPX / DJI / NASDAQ | C9: The underlying event tables (your original research, cleaned up) that every formula in this workbook pulls from. 2026 is included for the record but flagged amber and excluded from every stat - see note below.
A10: Data - Avg Path | C10: The trading-day-by-trading-day average index path (rebased to 100 at the election close) used to draw the N-pattern chart.
A12: A DATA ISSUE WE FOUND AND FIXED
A13: Your DJI and NASDAQ tabs had a 2026 row with 1-day/5-day/10-day return values already filled in, even though the 2026 midterm election (Nov 3, 2026) had not happened as of this report. Those figures can't be real yet, so they look like placeholder or test data left in the sheet. We kept the row for completeness (amber-flagged in the Data tabs) but excluded it from every average, probability, and statistical test in this workbook. Worth double-checking where those numbers came from before anyone else sees the file.
A15: METHODOLOGY & CAVEATS
A16: • Sample size is small (n=16 SPX/DJI cycles, n=13 Nasdaq cycles since Nasdaq composite data only goes back to 1974). Treat every probability as a historical frequency, not a forward guarantee.
A17: • Every cycle's macro backdrop was different (wars, Fed regimes, crises) - this is a seasonality study, not a causal model. The fundamentals column explains what likely drove each cycle, it does not prove the pattern will repeat for the same reasons.
A18: • 'Low/pre-low', 'retest' and 'shape' definitions follow your original workbook's methodology exactly - we did not redefine them.
A19: • All statistical tests (t-tests, binomial tests, correlations) were computed independently in Python (SciPy) and then rebuilt as live Excel formulas (TDIST, BINOMDIST, CORREL) - the two matched exactly, so the Excel formulas you see are reproducible and will recalculate if you edit the underlying data.
A20: • This is historical/statistical research, not investment advice.

Sheet Executive Summary
A1: Midterm-Election Seasonality Study - Executive Summary
A2: US equity markets, 16 midterm-election cycles (1962-2022) | S&P 500, Dow, Nasdaq | 2026 cycle in progress, not yet in the averages | Prepared November 01, 2026
A4: THE ONE-LINE TAKEAWAY
A5: Midterm-election years have, without exception in 16 straight cycles, finished the following six months higher - and by a wide margin (+14% average). That part is extremely well-supported. The 'dip-rally-dip-rally' N-shape you noticed is real on average, but a single clean N only shows up in roughly 3 years out of 10 - most years just climb without ever coming back down to retest the low. Pitch the destination (strong 6-12mo seasonality), not the exact route.
A9: WHAT WE'RE CONFIDENT ABOUT vs WHAT'S JUST A DESCRIPTIVE PATTERN
A10: HIGH CONFIDENCE
A11: • Stocks rally INTO election day - 16/16 SPX cycles, statistically significant (p<0.0001).
A12: • Stocks are higher 6 months after the election - 16/16 SPX, 15/16 DJI, 10/13 Nasdaq; p<0.05 on every index.
A13: • Midterm years outperform the other 3 years of the presidential cycle on average 6M/12M return (the well-documented 'midterm effect').
A15: MODERATE CONFIDENCE
A16: • A deeper post-election dip tends to precede a bigger 6-month rebound for DJI & Nasdaq (r=0.68-0.79, p<0.01) - weaker/absent for SPX.
A17: • A hotter rally INTO the election tends to borrow from, not add to, the 6-month move for DJI & Nasdaq (r=-0.56 to -0.71) - this is a mean-reversion signal, not a green light.
... A25: KEY NUMBERS AT A GLANCE
A26: 100% | D26: +13.8% | G26: 31% | J26: +14.2 pts
A27: of SPX cycles finished up 6 months after the election | D27: average SPX return, election close -> +6 months | G27: of SPX years actually traced a true 'N' retest | J27: SPX midterm-year 6M return advantage vs pre-election years
A29: WHERE TO GO NEXT IN THIS WORKBOOK
A30: YoY Fundamentals | D30: Year-by-year table: what macro event caused each dip, and how each index reacted.
A31: The N-Pattern Visualized | D31: The actual averaged chart your 'N' is based on, plus how often each shape really occurs.
A32: Probability Scorecard | D32: Every observation as a live, recalculating hit-rate with a plain-English read.
A33: Hypothesis Tests | D33: The statistical tests behind the 'high/moderate/low confidence' calls above.
A34: Midterm Cycle Effect | D34: Why midterm years specifically outperform the other 3 years of the presidential cycle.

Sheet YoY Fundamentals
A1: Midterm-Election Years: Year-by-Year Market Reaction & the Fundamental Story Behind It
A2: Every US midterm election since 1962. 'Catalyst' = the dominant macro driver into/out of that election. Returns are % price moves starting from the pre-election low / election-day close, as defined in the source study. 2026 is still in progress and excluded from every average and probability in this workbook.
A4: Year | B4: Election Date | C4: Catalyst | D4: What Happened (the fundamental story) | E4: Pre-Election Rally % (SPX) | F4: Post-Election Retest Drop % (SPX) | G4: Shape (SPX) | H4: SPX 6M Return | I4: DJI 6M Return | J4: NDQ 6M Return | K4: SPX 12M Return
A5: 1962 | B5: =IFERROR(TEXT(INDEX('Data - SPX'!$B:$B,MATCH($A5,'Data - SPX'!$A:$A,0)),"mmm d, yyyy"),TEXT(INDEX('Data - DJI'!$B:$B,MATCH($A5,'Data - DJI'!$A:$A,0)),"mmm d, yyyy")) -> Nov 6, 1962 | C5: Geopolitical / War: Cuban Missile Crisis | D5: Market was still digesting the spring 1962 'Kennedy Slide' when the Cuban Missile Crisis (Oct 16-28) pushed fear to a peak right before the election. Khrushchev's climb-down (Oct 28) removed the single biggest tail risk markets had priced in decades, triggering a relief rally. | E5: =IFERROR(IF(INDEX('Data - SPX'!$E:$E,MATCH($A5,'Data - SPX'!$A:$A,0))="","n/a",INDEX('Data - SPX'!$E:$E,MATCH($A5,'Data - SPX'!$A:$A,0))),"n/a") -> 11.04 | F5: =IFERROR(IF(INDEX('Data - SPX'!$I:$I,MATCH($A5,'Data - SPX'!$A:$A,0))="","n/a",INDEX('Data - SPX'!$I:$I,MATCH($A5,'Data - SPX'!$A:$A,0))),"n/a") -> -1.01 | G5: =IFERROR(IF(INDEX('Data - SPX'!$J:$J,MATCH($A5,'Data - SPX'!$A:$A,0))="","n/a",INDEX('Data - SPX'!$J:$J,MATCH($A5,'Data - SPX'!$A:$A,0))),"n/a") -> Higher low (no real retest) | H5: =IFERROR(IF(INDEX('Data - SPX'!$P:$P,MATCH($A5,'Data - SPX'!$A:$A,0))="","n/a",INDEX('Data - SPX'!$P:$P,MATCH($A5,'Data - SPX'!$A:$A,0))),"n/a") -> 19.16 | I5: =IFERROR(IF(INDEX('Data - DJI'!$P:$P,MATCH($A5,'Data - DJI'!$A:$A,0))="","n/a",INDEX('Data - DJI'!$P:$P,MATCH($A5,'Data - DJI'!$A:$A,0))),"n/a") -> 21.97 | J5: =IFERROR(IF(INDEX('Data - NASDAQ'!$P:$P,MATCH($A5,'Data - NASDAQ'!$A:$A,0))="","n/a",INDEX('Data - NASDAQ'!$P:$P,MATCH($A5,'Data - NASDAQ'!$A:$A,0))),"n/a") -> n/a | K5: =IFERROR(IF(INDEX('Data - SPX'!$Q:$Q,MATCH($A5,'Data - SPX'!$A:$A,0))="","n/a",INDEX('Data - SPX'!$Q:$Q,MATCH($A5,'Data - SPX'!$A:$A,0))),"n/a") -> 24.78
A6: 1966 | B6: =IFERROR(TEXT(INDEX('Data - SPX'!$B:$B,MATCH($A6,'Data - SPX'!$A:$A,0)),"mmm d, yyyy"),TEXT(INDEX('Data - DJI'!$B:$B,MATCH($A6,'Data - DJI'!$A:$A,0)),"mmm d, yyyy")) -> Nov 8, 1966 | C6: Fed Tightening: 1966 Credit Crunch | D6: The Fed tightened aggressively and Regulation Q deposit-rate ceilings caused a 'disintermediation' credit crunch, sparking recession fears into the election. The Fed eased in early 1967 and the economy achieved a rare soft landing, fueling the rebound. | E6: =IFERROR(IF(INDEX('Data - SPX'!$E:$E,MATCH($A6,'Data - SPX'!$A:$A,0))="","n/a",INDEX('Data - SPX'!$E:$E,MATCH($A6,'Data - SPX'!$A:$A,0))),"n/a") -> 11.69 | F6: =IFERROR(IF(INDEX('Data - SPX'!$I:$I,MATCH($A6,'Data - SPX'!$A:$A,0))="","n/a",INDEX('Data - SPX'!$I:$I,MATCH($A6,'Data - SPX'!$A:$A,0))),"n/a") -> -2.28 | G6: =IFERROR(IF(INDEX('Data - SPX'!$J:$J,MATCH($A6,'Data - SPX'!$A:$A,0))="","n/a",INDEX('Data - SPX'!$J:$J,MATCH($A6,'Data - SPX'!$A:$A,0))),"n/a") -> Higher low (no real retest) | H6: =IFERROR(IF(INDEX('Data - SPX'!$P:$P,MATCH($A6,'Data - SPX'!$A:$A,0))="","n/a",INDEX('Data - SPX'!$P:$P,MATCH($A6,'Data - SPX'!$A:$A,0))),"n/a") -> 17.16 | I6: =IFERROR(IF(INDEX('Data - DJI'!$P:$P,MATCH($A6,'Data - DJI'!$A:$A,0))="","n/a",INDEX('Data - DJI'!$P:$P,MATCH($A6,'Data - DJI'!$A:$A,0))),"n/a") -> 3.23 | J6: =IFERROR(IF(INDEX('Data - NASDAQ'!$P:$P,MATCH($A6,'Data - NASDAQ'!$A:$A,0))="","n/a",INDEX('Data - NASDAQ'!$P:$P,MATCH($A6,'Data - NASDAQ'!$A:$A,0))),"n/a") -> n/a | K6: =IFERROR(IF(INDEX('Data - SPX'!$Q:$Q,MATCH($A6,'Data - SPX'!$A:$A,0))="","n/a",INDEX('Data - SPX'!$Q:$Q,MATCH($A6,'Data - SPX'!$A:$A,0))),"n/a") -> 12.89
A7: 1970 | B7: =IFERROR(TEXT(INDEX('Data - SPX'!$B:$B,MATCH($A7,'Data - SPX'!$A:$A,0)),"mmm d, yyyy"),TEXT(INDEX('Data - DJI'!$B:$B,MATCH($A7,'Data - DJI'!$A:$A,0)),"mmm d, yyyy")) -> Nov 3, 1970 | C7: Financial / Credit Crisis: Penn Central bankruptcy | D7: The Penn Central Railroad's bankruptcy (Jun 1970) froze the commercial-paper market; the Fed (under Burns) opened the discount window to backstop liquidity. Combined with the economy exiting the 1969-70 recession, this liquidity rescue underpinned the rebound. | E7: =IFERROR(IF(INDEX('Data - SPX'!$E:$E,MATCH($A7,'Data - SPX'!$A:$A,0))="","n/a",INDEX('Data - SPX'!$E:$E,MATCH($A7,'Data - SPX'!$A:$A,0))),"n/a") -> 4.21 | F7: =IFERROR(IF(INDEX('Data - SPX'!$I:$I,MATCH($A7,'Data - SPX'!$A:$A,0))="","n/a",INDEX('Data - SPX'!$I:$I,MATCH($A7,'Data - SPX'!$A:$A,0))),"n/a") -> -2.36 | G7: =IFERROR(IF(INDEX('Data - SPX'!$J:$J,MATCH($A7,'Data - SPX'!$A:$A,0))="","n/a",INDEX('Data - SPX'!$J:$J,MATCH($A7,'Data - SPX'!$A:$A,0))),"n/a") -> N (retest ~ old low) | H7: =IFERROR(IF(INDEX('Data - SPX'!$P:$P,MATCH($A7,'Data - SPX'!$A:$A,0))="","n/a",INDEX('Data - SPX'!$P:$P,MATCH($A7,'Data - SPX'!$A:$A,0))),"n/a") -> 22.64 | I7: =IFERROR(IF(INDEX('Data - DJI'!$P:$P,MATCH($A7,'Data - DJI'!$A:$A,0))="","n/a",INDEX('Data - DJI'!$P:$P,MATCH($A7,'Data - DJI'!$A:$A,0))),"n/a") -> 15.41 | J7: =IFERROR(IF(INDEX('Data - NASDAQ'!$P:$P,MATCH($A7,'Data - NASDAQ'!$A:$A,0))="","n/a",INDEX('Data - NASDAQ'!$P:$P,MATCH($A7,'Data - NASDAQ'!$A:$A,0))),"n/a") -> n/a | K7: =IFERROR(IF(INDEX('Data - SPX'!$Q:$Q,MATCH($A7,'Data - SPX'!$A:$A,0))="","n/a",INDEX('Data - SPX'!$Q:$Q,MATCH($A7,'Data - SPX'!$A:$A,0))),"n/a") -> 12.69
A8: 1974 | B8: =IFERROR(TEXT(INDEX('Data - SPX'!$B:$B,MATCH($A8,'Data - SPX'!$A:$A,0)),"mmm d, yyyy"),TEXT(INDEX('Data - DJI'!$B:$B,MATCH($A8,'Data - DJI'!$A:$A,0)),"mmm d, yyyy")) -> Nov 5, 1974 | C8: Inflation Shock: Oil embargo / Watergate / Stagflation | D8: The 1973 OPEC oil embargo, double-digit inflation and Nixon's resignation (Aug 1974) drove the worst bear market since the Depression. By the October low, selling was exhausted and the Fed began easing - producing the largest rally in this dataset (+23% into the close alone). | E8: =IFERROR(IF(INDEX('Data - SPX'!$E:$E,MATCH($A8,'Data - SPX'!$A:$A,0))="","n/a",INDEX('Data - SPX'!$E:$E,MATCH($A8,'Data - SPX'!$A:$A,0))),"n/a") -> 23.21 | F8: =IFERROR(IF(INDEX('Data - SPX'!$I:$I,MATCH($A8,'Data - SPX'!$A:$A,0))="","n/a",INDEX('Data - SPX'!$I:$I,MATCH($A8,'Data - SPX'!$A:$A,0))),"n/a") -> -14.62 | G8: =IFERROR(IF(INDEX('Data - SPX'!$J:$J,MATCH($A8,'Data - SPX'!$A:$A,0))="","n/a",INDEX('Data - SPX'!$J:$J,MATCH($A8,'Data - SPX'!$A:$A,0))),"n/a") -> Higher low (no real retest) | H8: =IFERROR(IF(INDEX('Data - SPX'!$P:$P,MATCH($A8,'Data - SPX'!$A:$A,0))="","n/a",INDEX('Data - SPX'!$P:$P,MATCH($A8,'Data - SPX'!$A:$A,0))),"n/a") -> 19.93 | I8: =IFERROR(IF(INDEX('Data - DJI'!$P:$P,MATCH($A8,'Data - DJI'!$A:$A,0))="","n/a",INDEX('Data - DJI'!$P:$P,MATCH($A8,'Data - DJI'!$A:$A,0))),"n/a") -> 1.28 | J8: =IFERROR(IF(INDEX('Data - NASDAQ'!$P:$P,MATCH($A8,'Data - NASDAQ'!$A:$A,0))="","n/a",INDEX('Data - NASDAQ'!$P:$P,MATCH($A8,'Data - NASDAQ'!$A:$A,0))),"n/a") -> -9.63 | K8: =IFERROR(IF(INDEX('Data - SPX'!$Q:$Q,MATCH($A8,'Data - SPX'!$A:$A,0))="","n/a",INDEX('Data - SPX'!$Q:$Q,MATCH($A8,'Data - SPX'!$A:$A,0))),"n/a") -> 18.69
A9: 1978 | B9: =IFERROR(TEXT(INDEX('Data - SPX'!$B:$B,MATCH($A9,'Data - SPX'!$A:$A,0)),"mmm d, yyyy"),TEXT(INDEX('Data - DJI'!$B:$B,MATCH($A9,'Data - DJI'!$A:$A,0)),"mmm d, yyyy")) -> Nov 7, 1978 | C9: Inflation Shock: Dollar crisis / sluggish Fed | D9: Persistent inflation and a weak dollar continued under a Fed (G. William Miller) seen as slow to respond (Volcker was not appointed chair until Aug 1979). Moves were comparatively small both into and after the election. | E9: =IFERROR(IF(INDEX('Data - SPX'!$E:$E,MATCH($A9,'Data - SPX'!$A:$A,0))="","n/a",INDEX('Data - SPX'!$E:$E,MATCH($A9,'Data - SPX'!$A:$A,0))),"n/a") -> 2.4 | F9: =IFERROR(IF(INDEX('Data - SPX'!$I:$I,MATCH($A9,'Data - SPX'!$A:$A,0))="","n/a",INDEX('Data - SPX'!$I:$I,MATCH($A9,'Data - SPX'!$A:$A,0))),"n/a") -> -2.22 | G9: =IFERROR(IF(INDEX('Data - SPX'!$J:$J,MATCH($A9,'Data - SPX'!$A:$A,0))="","n/a",INDEX('Data - SPX'!$J:$J,MATCH($A9,'Data - SPX'!$A:$A,0))),"n/a") -> N (retest ~ old low) | H9: =IFERROR(IF(INDEX('Data - SPX'!$P:$P,MATCH($A9,'Data - SPX'!$A:$A,0))="","n/a",INDEX('Data - SPX'!$P:$P,MATCH($A9,'Data - SPX'!$A:$A,0))),"n/a") -> 5.51 | I9: =IFERROR(IF(INDEX('Data - DJI'!$P:$P,MATCH($A9,'Data - DJI'!$A:$A,0))="","n/a",INDEX('Data - DJI'!$P:$P,MATCH($A9,'Data - DJI'!$A:$A,0))),"n/a") -> 1.76 | J9: =IFERROR(IF(INDEX('Data - NASDAQ'!$P:$P,MATCH($A9,'Data - NASDAQ'!$A:$A,0))="","n/a",INDEX('Data - NASDAQ'!$P:$P,MATCH($A9,'Data - NASDAQ'!$A:$A,0))),"n/a") -> 14.99 | K9: =IFERROR(IF(INDEX('Data - SPX'!$Q:$Q,MATCH($A9,'Data - SPX'!$A:$A,0))="","n/a",INDEX('Data - SPX'!$Q:$Q,MATCH($A9,'Data - SPX'!$A:$A,0))),"n/a") -> 6.41
A10: 1982 | B10: =IFERROR(TEXT(INDEX('Data - SPX'!$B:$B,MATCH($A10,'Data - SPX'!$A:$A,0)),"mmm d, yyyy"),TEXT(INDEX('Data - DJI'!$B:$B,MATCH($A10,'Data - DJI'!$A:$A,0)),"mmm d, yyyy")) -> Nov 2, 1982 | C10: Recession: Volcker disinflation / recession trough | D10: Volcker's rate shock broke 1970s inflation but caused the brutal 1981-82 recession (unemployment >10%). By Aug-Oct 1982 inflation was clearly breaking and the Fed pivoted to easing - the starting gun for an 18-year secular bull market. | E10: =IFERROR(IF(INDEX('Data - SPX'!$E:$E,MATCH($A10,'Data - SPX'!$A:$A,0))="","n/a",INDEX('Data - SPX'!$E:$E,MATCH($A10,'Data - SPX'!$A:$A,0))),"n/a") -> 4.56 | F10: =IFERROR(IF(INDEX('Data - SPX'!$I:$I,MATCH($A10,'Data - SPX'!$A:$A,0))="","n/a",INDEX('Data - SPX'!$I:$I,MATCH($A10,'Data - SPX'!$A:$A,0))),"n/a") -> -4.43 | G10: =IFERROR(IF(INDEX('Data - SPX'!$J:$J,MATCH($A10,'Data - SPX'!$A:$A,0))="","n/a",INDEX('Data - SPX'!$J:$J,MATCH($A10,'Data - SPX'!$A:$A,0))),"n/a") -> N (retest ~ old low) | H10: =IFERROR(IF(INDEX('Data - SPX'!$P:$P,MATCH($A10,'Data - SPX'!$A:$A,0))="","n/a",INDEX('Data - SPX'!$P:$P,MATCH($A10,'Data - SPX'!$A:$A,0))),"n/a") -> 17.91 | I10: =IFERROR(IF(INDEX('Data - DJI'!$P:$P,MATCH($A10,'Data - DJI'!$A:$A,0))="","n/a",INDEX('Data - DJI'!$P:$P,MATCH($A10,'Data - DJI'!$A:$A,0))),"n/a") -> 25.18 | J10: =IFERROR(IF(INDEX('Data - NASDAQ'!$P:$P,MATCH($A10,'Data - NASDAQ'!$A:$A,0))="","n/a",INDEX('Data - NASDAQ'!$P:$P,MATCH($A10,'Data - NASDAQ'!$A:$A,0))),"n/a") -> 27.7 | K10: =IFERROR(IF(INDEX('Data - SPX'!$Q:$Q,MATCH($A10,'Data - SPX'!$A:$A,0))="","n/a",INDEX('Data - SPX'!$Q:$Q,MATCH($A10,'Data - SPX'!$A:$A,0))),"n/a") -> 19.89
A11: 1986 | B11: =IFERROR(TEXT(INDEX('Data - SPX'!$B:$B,MATCH($A11,'Data - SPX'!$A:$A,0)),"mmm d, yyyy"),TEXT(INDEX('Data - DJI'!$B:$B,MATCH($A11,'Data - DJI'!$A:$A,0)),"mmm d, yyyy")) -> Nov 4, 1986 | C11: Valuation Reset: Tax reform / oil price collapse | D11: The 1986 Tax Reform Act and an OPEC-driven oil price collapse added uncertainty into an already extended bull run; Iran-Contra broke publicly in November. Moves were modest - this was the calm before the Oct 1987 crash, not yet visible in the data. | E11: =IFERROR(IF(INDEX('Data - SPX'!$E:$E,MATCH($A11,'Data - SPX'!$A:$A,0))="","n/a",INDEX('Data - SPX'!$E:$E,MATCH($A11,'Data - SPX'!$A:$A,0))),"n/a") -> 7.94 | F11: =IFERROR(IF(INDEX('Data - SPX'!$I:$I,MATCH($A11,'Data - SPX'!$A:$A,0))="","n/a",INDEX('Data - SPX'!$I:$I,MATCH($A11,'Data - SPX'!$A:$A,0))),"n/a") -> -4.34 | G11: =IFERROR(IF(INDEX('Data - SPX'!$J:$J,MATCH($A11,'Data - SPX'!$A:$A,0))="","n/a",INDEX('Data - SPX'!$J:$J,MATCH($A11,'Data - SPX'!$A:$A,0))),"n/a") -> Higher low (no real retest) | H11: =IFERROR(IF(INDEX('Data - SPX'!$P:$P,MATCH($A11,'Data - SPX'!$A:$A,0))="","n/a",INDEX('Data - SPX'!$P:$P,MATCH($A11,'Data - SPX'!$A:$A,0))),"n/a") -> 17.53 | I11: =IFERROR(IF(INDEX('Data - DJI'!$P:$P,MATCH($A11,'Data - DJI'!$A:$A,0))="","n/a",INDEX('Data - DJI'!$P:$P,MATCH($A11,'Data - DJI'!$A:$A,0))),"n/a") -> 27.16 | J11: =IFERROR(IF(INDEX('Data - NASDAQ'!$P:$P,MATCH($A11,'Data - NASDAQ'!$A:$A,0))="","n/a",INDEX('Data - NASDAQ'!$P:$P,MATCH($A11,'Data - NASDAQ'!$A:$A,0))),"n/a") -> 13.22 | K11: =IFERROR(IF(INDEX('Data - SPX'!$Q:$Q,MATCH($A11,'Data - SPX'!$A:$A,0))="","n/a",INDEX('Data - SPX'!$Q:$Q,MATCH($A11,'Data - SPX'!$A:$A,0))),"n/a") -> 1.12
A12: 1990 | B12: =IFERROR(TEXT(INDEX('Data - SPX'!$B:$B,MATCH($A12,'Data - SPX'!$A:$A,0)),"mmm d, yyyy"),TEXT(INDEX('Data - DJI'!$B:$B,MATCH($A12,'Data - DJI'!$A:$A,0)),"mmm d, yyyy")) -> Nov 6, 1990 | C12: Geopolitical / War: Gulf War / oil shock / S&L crisis | D12: Iraq's invasion of Kuwait (Aug 1990) spiked oil prices and the S&L crisis stressed banks just as the economy tipped into recession (Jul 1990-Mar 1991). The market bottomed in October, well ahead of the swift Jan 1991 Desert Storm resolution, and rallied on that clarity. | E12: =IFERROR(IF(INDEX('Data - SPX'!$E:$E,MATCH($A12,'Data - SPX'!$A:$A,0))="","n/a",INDEX('Data - SPX'!$E:$E,MATCH($A12,'Data - SPX'!$A:$A,0))),"n/a") -> 5.81 | F12: =IFERROR(IF(INDEX('Data - SPX'!$I:$I,MATCH($A12,'Data - SPX'!$A:$A,0))="","n/a",INDEX('Data - SPX'!$I:$I,MATCH($A12,'Data - SPX'!$A:$A,0))),"n/a") -> -2.11 | G12: =IFERROR(IF(INDEX('Data - SPX'!$J:$J,MATCH($A12,'Data - SPX'!$A:$A,0))="","n/a",INDEX('Data - SPX'!$J:$J,MATCH($A12,'Data - SPX'!$A:$A,0))),"n/a") -> Higher low (no real retest) | H12: =IFERROR(IF(INDEX('Data - SPX'!$P:$P,MATCH($A12,'Data - SPX'!$A:$A,0))="","n/a",INDEX('Data - SPX'!$P:$P,MATCH($A12,'Data - SPX'!$A:$A,0))),"n/a") -> 21.97 | I12: =IFERROR(IF(INDEX('Data - DJI'!$P:$P,MATCH($A12,'Data - DJI'!$A:$A,0))="","n/a",INDEX('Data - DJI'!$P:$P,MATCH($A12,'Data - DJI'!$A:$A,0))),"n/a") -> 3.9 | J12: =IFERROR(IF(INDEX('Data - NASDAQ'!$P:$P,MATCH($A12,'Data - NASDAQ'!$A:$A,0))="","n/a",INDEX('Data - NASDAQ'!$P:$P,MATCH($A12,'Data - NASDAQ'!$A:$A,0))),"n/a") -> 9.16 | K12: =IFERROR(IF(INDEX('Data - SPX'!$Q:$Q,MATCH($A12,'Data - SPX'!$A:$A,0))="","n/a",INDEX('Data - SPX'!$Q:$Q,MATCH($A12,'Data - SPX'!$A:$A,0))),"n/a") -> 25.14
A13: 1994 | B13: =IFERROR(TEXT(INDEX('Data - SPX'!$B:$B,MATCH($A13,'Data - SPX'!$A:$A,0)),"mmm d, yyyy"),TEXT(INDEX('Data - DJI'!$B:$B,MATCH($A13,'Data - DJI'!$A:$A,0)),"mmm d, yyyy")) -> Nov 8, 1994 | C13: Fed Tightening: 'Bond Massacre' rate-hike cycle | D13: Greenspan's Fed doubled the funds rate from 3% to 6% over 1994 - the worst year for bonds in decades - and a Mexican peso crisis emerged in December. Equities chopped sideways most of the year, then rallied once the hiking cycle visibly neared its end (final hike Feb 1995). | E13: =IFERROR(IF(INDEX('Data - SPX'!$E:$E,MATCH($A13,'Data - SPX'!$A:$A,0))="","n/a",INDEX('Data - SPX'!$E:$E,MATCH($A13,'Data - SPX'!$A:$A,0))),"n/a") -> 3.65 | F13: =IFERROR(IF(INDEX('Data - SPX'!$I:$I,MATCH($A13,'Data - SPX'!$A:$A,0))="","n/a",INDEX('Data - SPX'!$I:$I,MATCH($A13,'Data - SPX'!$A:$A,0))),"n/a") -> -4.89 | G13: =IFERROR(IF(INDEX('Data - SPX'!$J:$J,MATCH($A13,'Data - SPX'!$A:$A,0))="","n/a",INDEX('Data - SPX'!$J:$J,MATCH($A13,'Data - SPX'!$A:$A,0))),"n/a") -> N (retest ~ old low) | H13: =IFERROR(IF(INDEX('Data - SPX'!$P:$P,MATCH($A13,'Data - SPX'!$A:$A,0))="","n/a",INDEX('Data - SPX'!$P:$P,MATCH($A13,'Data - SPX'!$A:$A,0))),"n/a") -> 12.52 | I13: =IFERROR(IF(INDEX('Data - DJI'!$P:$P,MATCH($A13,'Data - DJI'!$A:$A,0))="","n/a",INDEX('Data - DJI'!$P:$P,MATCH($A13,'Data - DJI'!$A:$A,0))),"n/a") -> 23.04 | J13: =IFERROR(IF(INDEX('Data - NASDAQ'!$P:$P,MATCH($A13,'Data - NASDAQ'!$A:$A,0))="","n/a",INDEX('Data - NASDAQ'!$P:$P,MATCH($A13,'Data - NASDAQ'!$A:$A,0))),"n/a") -> 29.33 | K13: =IFERROR(IF(INDEX('Data - SPX'!$Q:$Q,MATCH($A13,'Data - SPX'!$A:$A,0))="","n/a",INDEX('Data - SPX'!$Q:$Q,MATCH($A13,'Data - SPX'!$A:$A,0))),"n/a") -> 27.07
A14: 1998 | B14: =IFERROR(TEXT(INDEX('Data - SPX'!$B:$B,MATCH($A14,'Data - SPX'!$A:$A,0)),"mmm d, yyyy"),TEXT(INDEX('Data - DJI'!$B:$B,MATCH($A14,'Data - DJI'!$A:$A,0)),"mmm d, yyyy")) -> Nov 3, 1998 | C14: Financial / Credit Crisis: Russia default / LTCM collapse | D14: Russia's August 1998 debt default and the collapse of hedge fund LTCM in September triggered a sharp global liquidity scare. The Fed cut rates three times in quick succession (Sep-Nov 1998), producing the fastest V-shaped recovery in the dataset and feeding the dot-com mania. | E14: =IFERROR(IF(INDEX('Data - SPX'!$E:$E,MATCH($A14,'Data - SPX'!$A:$A,0))="","n/a",INDEX('Data - SPX'!$E:$E,MATCH($A14,'Data - SPX'!$A:$A,0))),"n/a") -> 20.31 | F14: =IFERROR(IF(INDEX('Data - SPX'!$I:$I,MATCH($A14,'Data - SPX'!$A:$A,0))="","n/a",INDEX('Data - SPX'!$I:$I,MATCH($A14,'Data - SPX'!$A:$A,0))),"n/a") -> -0.12 | G14: =IFERROR(IF(INDEX('Data - SPX'!$J:$J,MATCH($A14,'Data - SPX'!$A:$A,0))="","n/a",INDEX('Data - SPX'!$J:$J,MATCH($A14,'Data - SPX'!$A:$A,0))),"n/a") -> Higher low (no real retest) | H14: =IFERROR(IF(INDEX('Data - SPX'!$P:$P,MATCH($A14,'Data - SPX'!$A:$A,0))="","n/a",INDEX('Data - SPX'!$P:$P,MATCH($A14,'Data - SPX'!$A:$A,0))),"n/a") -> 21.95 | I14: =IFERROR(IF(INDEX('Data - DJI'!$P:$P,MATCH($A14,'Data - DJI'!$A:$A,0))="","n/a",INDEX('Data - DJI'!$P:$P,MATCH($A14,'Data - DJI'!$A:$A,0))),"n/a") -> 12.22 | J14: =IFERROR(IF(INDEX('Data - NASDAQ'!$P:$P,MATCH($A14,'Data - NASDAQ'!$A:$A,0))="","n/a",INDEX('Data - NASDAQ'!$P:$P,MATCH($A14,'Data - NASDAQ'!$A:$A,0))),"n/a") -> 33.03 | K14: =IFERROR(IF(INDEX('Data - SPX'!$Q:$Q,MATCH($A14,'Data - SPX'!$A:$A,0))="","n/a",INDEX('Data - SPX'!$Q:$Q,MATCH($A14,'Data - SPX'!$A:$A,0))),"n/a") -> 21.97
A15: 2002 | B15: =IFERROR(TEXT(INDEX('Data - SPX'!$B:$B,MATCH($A15,'Data - SPX'!$A:$A,0)),"mmm d, yyyy"),TEXT(INDEX('Data - DJI'!$B:$B,MATCH($A15,'Data - DJI'!$A:$A,0)),"mmm d, yyyy")) -> Nov 5, 2002 | C15: Valuation Reset: Dot-com bust / accounting scandals | D15: The tail of the 2000-02 bear market, WorldCom/accounting scandals and an impending Iraq War weighed on sentiment. The October 2002 low marked the cyclical bottom of the bear market, and the subsequent rally was the simple mechanical result of extreme prior oversold conditions. | E15: =IFERROR(IF(INDEX('Data - SPX'!$E:$E,MATCH($A15,'Data - SPX'!$A:$A,0))="","n/a",INDEX('Data - SPX'!$E:$E,MATCH($A15,'Data - SPX'!$A:$A,0))),"n/a") -> 19.1 | F15: =IFERROR(IF(INDEX('Data - SPX'!$I:$I,MATCH($A15,'Data - SPX'!$A:$A,0))="","n/a",INDEX('Data - SPX'!$I:$I,MATCH($A15,'Data - SPX'!$A:$A,0))),"n/a") -> -5.02 | G15: =IFERROR(IF(INDEX('Data - SPX'!$J:$J,MATCH($A15,'Data - SPX'!$A:$A,0))="","n/a",INDEX('Data - SPX'!$J:$J,MATCH($A15,'Data - SPX'!$A:$A,0))),"n/a") -> Higher low (no real retest) | H15: =IFERROR(IF(INDEX('Data - SPX'!$P:$P,MATCH($A15,'Data - SPX'!$A:$A,0))="","n/a",INDEX('Data - SPX'!$P:$P,MATCH($A15,'Data - SPX'!$A:$A,0))),"n/a") -> 1.22 | I15: =IFERROR(IF(INDEX('Data - DJI'!$P:$P,MATCH($A15,'Data - DJI'!$A:$A,0))="","n/a",INDEX('Data - DJI'!$P:$P,MATCH($A15,'Data - DJI'!$A:$A,0))),"n/a") -> -16.16 | J15: =IFERROR(IF(INDEX('Data - NASDAQ'!$P:$P,MATCH($A15,'Data - NASDAQ'!$A:$A,0))="","n/a",INDEX('Data - NASDAQ'!$P:$P,MATCH($A15,'Data - NASDAQ'!$A:$A,0))),"n/a") -> -12.82 | K15: =IFERROR(IF(INDEX('Data - SPX'!$Q:$Q,MATCH($A15,'Data - SPX'!$A:$A,0))="","n/a",INDEX('Data - SPX'!$Q:$Q,MATCH($A15,'Data - SPX'!$A:$A,0))),"n/a") -> 14.9
A16: 2006 | B16: =IFERROR(TEXT(INDEX('Data - SPX'!$B:$B,MATCH($A16,'Data - SPX'!$A:$A,0)),"mmm d, yyyy"),TEXT(INDEX('Data - DJI'!$B:$B,MATCH($A16,'Data - DJI'!$A:$A,0)),"mmm d, yyyy")) -> Nov 7, 2006 | C16: Calm / Low Volatility: Fed pause, pre-housing-crisis calm | D16: The Fed had just finished hiking (last move Jun 2006) and the housing market was only beginning to cool - genuine crisis conditions were still a year away. This is the lowest-volatility cycle in the dataset. | E16: =IFERROR(IF(INDEX('Data - SPX'!$E:$E,MATCH($A16,'Data - SPX'!$A:$A,0))="","n/a",INDEX('Data - SPX'!$E:$E,MATCH($A16,'Data - SPX'!$A:$A,0))),"n/a") -> 1.61 | F16: =IFERROR(IF(INDEX('Data - SPX'!$I:$I,MATCH($A16,'Data - SPX'!$A:$A,0))="","n/a",INDEX('Data - SPX'!$I:$I,MATCH($A16,'Data - SPX'!$A:$A,0))),"n/a") -> -0.52 | G16: =IFERROR(IF(INDEX('Data - SPX'!$J:$J,MATCH($A16,'Data - SPX'!$A:$A,0))="","n/a",INDEX('Data - SPX'!$J:$J,MATCH($A16,'Data - SPX'!$A:$A,0))),"n/a") -> No pre-election rally | H16: =IFERROR(IF(INDEX('Data - SPX'!$P:$P,MATCH($A16,'Data - SPX'!$A:$A,0))="","n/a",INDEX('Data - SPX'!$P:$P,MATCH($A16,'Data - SPX'!$A:$A,0))),"n/a") -> 9.16 | I16: =IFERROR(IF(INDEX('Data - DJI'!$P:$P,MATCH($A16,'Data - DJI'!$A:$A,0))="","n/a",INDEX('Data - DJI'!$P:$P,MATCH($A16,'Data - DJI'!$A:$A,0))),"n/a") -> 21.83 | J16: =IFERROR(IF(INDEX('Data - NASDAQ'!$P:$P,MATCH($A16,'Data - NASDAQ'!$A:$A,0))="","n/a",INDEX('Data - NASDAQ'!$P:$P,MATCH($A16,'Data - NASDAQ'!$A:$A,0))),"n/a") -> 24.79 | K16: =IFERROR(IF(INDEX('Data - SPX'!$Q:$Q,MATCH($A16,'Data - SPX'!$A:$A,0))="","n/a",INDEX('Data - SPX'!$Q:$Q,MATCH($A16,'Data - SPX'!$A:$A,0))),"n/a") -> 6.71
... A21: 2026 | B21: =IFERROR(TEXT(INDEX('Data - SPX'!$B:$B,MATCH($A21,'Data - SPX'!$A:$A,0)),"mmm d, yyyy"),TEXT(INDEX('Data - DJI'!$B:$B,MATCH($A21,'Data - DJI'!$A:$A,0)),"mmm d, yyyy")) -> Nov 3, 2026 | C21: DATA INCOMPLETE: Election not yet held (Nov 3, 2026) | D21: This row is still in progress: the election has not occurred as of this report, so post-election fields (retest, 3m/6m/12m returns) are blank by design. The 1d/5d/10d/1m return figures entered in the source file predate the election and should not be used - they appear to be placeholder/test values and are excluded from every statistic in this workbook. | E21: =IFERROR(IF(INDEX('Data - SPX'!$E:$E,MATCH($A21,'Data - SPX'!$A:$A,0))="","n/a",INDEX('Data - SPX'!$E:$E,MATCH($A21,'Data - SPX'!$A:$A,0))),"n/a") -> n/a | F21: =IFERROR(IF(INDEX('Data - SPX'!$I:$I,MATCH($A21,'Data - SPX'!$A:$A,0))="","n/a",INDEX('Data - SPX'!$I:$I,MATCH($A21,'Data - SPX'!$A:$A,0))),"n/a") -> n/a | G21: =IFERROR(IF(INDEX('Data - SPX'!$J:$J,MATCH($A21,'Data - SPX'!$A:$A,0))="","n/a",INDEX('Data - SPX'!$J:$J,MATCH($A21,'Data - SPX'!$A:$A,0))),"n/a") -> n/a | H21: =IFERROR(IF(INDEX('Data - SPX'!$P:$P,MATCH($A21,'Data - SPX'!$A:$A,0))="","n/a",INDEX('Data - SPX'!$P:$P,MATCH($A21,'Data - SPX'!$A:$A,0))),"n/a") -> n/a | I21: =IFERROR(IF(INDEX('Data - DJI'!$P:$P,MATCH($A21,'Data - DJI'!$A:$A,0))="","n/a",INDEX('Data - DJI'!$P:$P,MATCH($A21,'Data - DJI'!$A:$A,0))),"n/a") -> n/a | J21: =IFERROR(IF(INDEX('Data - NASDAQ'!$P:$P,MATCH($A21,'Data - NASDAQ'!$A:$A,0))="","n/a",INDEX('Data - NASDAQ'!$P:$P,MATCH($A21,'Data - NASDAQ'!$A:$A,0))),"n/a") -> n/a | K21: =IFERROR(IF(INDEX('Data - SPX'!$Q:$Q,MATCH($A21,'Data - SPX'!$A:$A,0))="","n/a",INDEX('Data - SPX'!$Q:$Q,MATCH($A21,'Data - SPX'!$A:$A,0))),"n/a") -> n/a

Sheet The N-Pattern Visualized
A1: The Average Path: What Actually Happens Around a Midterm Election
A2: Average of every completed cycle, each index rebased to 100 at the election-day close. Trading day 0 = election day. This is the 'N' you were seeing - averaged across history it is real, even though any single year rarely traces it this cleanly (see Probability Scorecard).
A32: Reading the curve, left to right:
A33: Day -30 to ~-10 | B33: PRE-ELECTION DIP | D33: Index drifts to its cycle low. On average this is the single worst stretch of the whole window.
A34: ~Day -10 to 0 | B34: RALLY INTO THE ELECTION | D34: Markets climb into election day itself - this leg is up in 100% of SPX years and ~81% of DJI years.
A35: Day 0 to ~+20/+30 | B35: POST-ELECTION CHOP / RETEST | D35: A flatter, choppier stretch where the second dip of a true 'N' would occur - but only in a minority of years does it actually retest the old low.
A36: ~Day +40 to +130 | B36: THE 6-MONTH RALLY | D36: The dominant, most reliable leg: index levels run roughly 10-16% above the election close by six months out, across all three indices.
A39: How Often Does Each Shape Actually Occur? (this is the honesty check on the 'N' story)
A40: Shape | B40: SPX | C40: DJI | D40: NASDAQ
A41: Higher low (no real retest) | B41: 0.5625 | C41: 0.125 | D41: 0.15384615
A42: N (retest ~ old low) | B42: 0.3125 | C42: 0.3125 | D42: 0.15384615
A43: N (retest makes lower low) | B43: 0.0625 | C43: 0.25 | D43: 0.23076923
A44: No pre-election rally | B44: 0.0625 | C44: 0.3125 | D44: 0.46153846

Sheet Probability Scorecard
A1: Probability Scorecard - How Often Has Each Part of the Pattern Actually Happened?
A2: Historical hit-rate for each observation, 1962-2022 (n=16 SPX/DJI cycles, n=13 Nasdaq cycles - 2026 excluded as incomplete). These are simple historical frequencies, not forward-looking guarantees. Small sample sizes (n<20) mean single outlier years can move a percentage a lot.
A4: Observation | B4: SPX | C4: DJI | D4: NASDAQ | E4: Read for a non-technical stakeholder
A5: Market rallies into election day (low -> election close is UP) | B5: =COUNTIF('Data - SPX'!$E$5:$E$20,">0")/(20-5+1) -> 1 | C5: =COUNTIF('Data - DJI'!$E$5:$E$20,">0")/(20-5+1) -> 0.8125 | D5: =COUNTIF('Data - NASDAQ'!$E$5:$E$17,">0")/(17-5+1) -> 0.61538462 | E5: Near-certain. In 16/16 SPX cycles stocks rose from the pre-election low into election day.
A6: That pre-election rally is >= 5% | B6: =COUNTIF('Data - SPX'!$E$5:$E$20,">=5")/(20-5+1) -> 0.625 | C6: =COUNTIF('Data - DJI'!$E$5:$E$20,">=5")/(20-5+1) -> 0.4375 | D6: =COUNTIF('Data - NASDAQ'!$E$5:$E$17,">=5")/(17-5+1) -> 0.53846154 | E6: A real rally, not noise - happens about 6 times in 10.
A7: Day after the election is UP | B7: =COUNTIF('Data - SPX'!$K$5:$K$20,">0")/(20-5+1) -> 0.75 | C7: =COUNTIF('Data - DJI'!$K$5:$K$20,">0")/(20-5+1) -> 0.5 | D7: =COUNTIF('Data - NASDAQ'!$K$5:$K$17,">0")/(17-5+1) -> 0.61538462 | E7: Coin-flip-to-favorable. Don't read too much into the very next day.
A8: Market is UP 3 months after the election | B8: =COUNTIF('Data - SPX'!$O$5:$O$20,">0")/(20-5+1) -> 0.875 | C8: =COUNTIF('Data - DJI'!$O$5:$O$20,">0")/(20-5+1) -> 0.9375 | D8: =COUNTIF('Data - NASDAQ'!$O$5:$O$17,">0")/(17-5+1) -> 0.84615385 | E8: Strong favorable odds across all three indices.
A9: Market is UP 6 months after the election | B9: =COUNTIF('Data - SPX'!$P$5:$P$20,">0")/(20-5+1) -> 1 | C9: =COUNTIF('Data - DJI'!$P$5:$P$20,">0")/(20-5+1) -> 0.9375 | D9: =COUNTIF('Data - NASDAQ'!$P$5:$P$17,">0")/(17-5+1) -> 0.76923077 | E9: The single most reliable number in this whole study.
A10: Market is UP 12 months after the election | B10: =COUNTIF('Data - SPX'!$Q$5:$Q$20,">0")/(20-5+1) -> 1 | C10: =COUNTIF('Data - DJI'!$Q$5:$Q$20,">0")/(20-5+1) -> 0.875 | D10: =COUNTIF('Data - NASDAQ'!$Q$5:$Q$17,">0")/(17-5+1) -> 0.84615385 | E10: Still strongly favorable, though further out and more can intervene.
A11: 6-month return is a strong gain (>=10%) | B11: =COUNTIF('Data - SPX'!$P$5:$P$20,">=10")/(20-5+1) -> 0.625 | C11: =COUNTIF('Data - DJI'!$P$5:$P$20,">=10")/(20-5+1) -> 0.5625 | D11: =COUNTIF('Data - NASDAQ'!$P$5:$P$17,">=10")/(17-5+1) -> 0.61538462 | E11: More than half the time the 6-month move isn't just positive, it's a big move.
A12: A genuine 'N' forms: price drops back near/below the pre-election low after the rally | B12: =COUNTIF('Data - SPX'!$J$5:$J$20,"N*")/(20-5+1) -> 0.4375 | C12: =COUNTIF('Data - DJI'!$J$5:$J$20,"N*")/(20-5+1) -> 0.875 | D12: =COUNTIF('Data - NASDAQ'!$J$5:$J$17,"N*")/(17-5+1) -> 0.84615385 | E12: This is the part your 'N' story depends on - and it's the MINORITY outcome, not the typical one (see note below).
A13: Where a retest happens, it takes price >=5% below the election-day close | B13: =COUNTIFS('Data - SPX'!$I$5:$I$20,"<>",'Data - SPX'!$I$5:$I$20,"<=-5")/COUNTIF('Data - SPX'!$I$5:$I$20,"<>") -> 0.1875 | C13: =COUNTIFS('Data - DJI'!$I$5:$I$20,"<>",'Data - DJI'!$I$5:$I$20,"<=-5")/COUNTIF('Data - DJI'!$I$5:$I$20,"<>") -> 0.6875 | D13: =COUNTIFS('Data - NASDAQ'!$I$5:$I$17,"<>",'Data - NASDAQ'!$I$5:$I$17,"<=-5")/COUNTIF('Data - NASDAQ'!$I$5:$I$17,"<>") -> 0.69230769 | E13: A real post-election scare is possible but is the exception, not the rule.
A14: The eventual low in the 6 months after the election is BELOW the election-day close | B14: =COUNTIF('Data - SPX'!$T$5:$T$20,"<0")/(20-5+1) -> 1 | C14: =COUNTIF('Data - DJI'!$T$5:$T$20,"<0")/(20-5+1) -> 1 | D14: =COUNTIF('Data - NASDAQ'!$T$5:$T$17,"<0")/(17-5+1) -> 1 | E14: Almost certain - there is nearly always at least a small post-election wobble somewhere in the next 6 months, even in years that finish strongly up.
A16: IMPORTANT CONTEXT ON THE 'N' SHAPE: a true N (dip, rally into the election, a second dip back near the old low, then a rally) only happened in 5 of 16 SPX years (31%), 5 of 16 DJI years (31%), and 2 of 13 Nasdaq years (15%). The far more common shape is 'higher low' - price never comes back down near the old low at all, it just keeps climbing. The reliable part of the pattern is the destination (strong 6-12 month returns), not the literal N-shaped route getting there.

Sheet Hypothesis Tests
A1: Does Any of This Hold Up Statistically? Four Tests on the Underlying Data
A2: Formal tests run on the 1962-2022 event data (n=16 SPX/DJI, n=13 Nasdaq). Treat all of this as suggestive, not proof: a 16-point sample cannot establish causation, and every midterm cycle overlaps with the one before and after it (the data points are not fully independent).
A4: Test 1 - Is the average 6-month post-election return actually different from zero?
A5: One-sample t-test on Ret 6m % across all completed cycles. H0: true mean 6-month return = 0%.
A6: Index | B6: n | C6: Mean 6M Return | D6: Std Dev | E6: t-stat | F6: p-value (two-tail)
A7: SPX | B7: =COUNT('Data - SPX'!$P$5:$P$20) -> 16 | C7: =AVERAGE('Data - SPX'!$P$5:$P$20)/100 -> 0.1377 | D7: =STDEV('Data - SPX'!$P$5:$P$20)/100 -> 0.069891974 | E7: =C7/(D7/SQRT(B7)) -> 7.8807332 | F7: =TDIST(ABS(E7),B7-1,2) -> 1.0355601e-06
A8: DJI | B8: =COUNT('Data - DJI'!$P$5:$P$20) -> 16 | C8: =AVERAGE('Data - DJI'!$P$5:$P$20)/100 -> 0.1082875 | D8: =STDEV('Data - DJI'!$P$5:$P$20)/100 -> 0.11798643 | E8: =C8/(D8/SQRT(B8)) -> 3.671185 | F8: =TDIST(ABS(E8),B8-1,2) -> 0.002269161
A9: NASDAQ | B9: =COUNT('Data - NASDAQ'!$P$5:$P$17) -> 13 | C9: =AVERAGE('Data - NASDAQ'!$P$5:$P$17)/100 -> 0.14251538 | D9: =STDEV('Data - NASDAQ'!$P$5:$P$17)/100 -> 0.14950105 | E9: =C9/(D9/SQRT(B9)) -> 3.4370764 | F9: =TDIST(ABS(E9),B9-1,2) -> 0.0049209551
A10: Read: p < 0.05 means the average post-election rally is very unlikely to be pure noise around zero. All three indices clear that bar comfortably.
A12: Test 2 - Is 'up 6 months later' happening more often than a coin flip?
A13: One-sided binomial test. H0: true probability of a positive 6-month return = 50% (pure chance).
A14: Index | B14: Up-years | C14: n | D14: Observed % | E14: P(this many or more heads | fair coin) | F14: Verdict
A15: SPX | B15: =COUNTIF('Data - SPX'!$P$5:$P$20,">0") -> 16 | C15: =COUNT('Data - SPX'!$P$5:$P$20) -> 16 | D15: =B15/C15 -> 1 | E15: =1-BINOMDIST(B15-1,C15,0.5,TRUE()) -> 1.5258789e-05 | F15: =IF(E15<0.05,"Significant at 5%","Not significant") -> Significant at 5%
A16: DJI | B16: =COUNTIF('Data - DJI'!$P$5:$P$20,">0") -> 15 | C16: =COUNT('Data - DJI'!$P$5:$P$20) -> 16 | D16: =B16/C16 -> 0.9375 | E16: =1-BINOMDIST(B16-1,C16,0.5,TRUE()) -> 0.00025939941 | F16: =IF(E16<0.05,"Significant at 5%","Not significant") -> Significant at 5%
A17: NASDAQ | B17: =COUNTIF('Data - NASDAQ'!$P$5:$P$17,">0") -> 10 | C17: =COUNT('Data - NASDAQ'!$P$5:$P$17) -> 13 | D17: =B17/C17 -> 0.76923077 | E17: =1-BINOMDIST(B17-1,C17,0.5,TRUE()) -> 0.046142578 | F17: =IF(E17<0.05,"Significant at 5%","Not significant") -> Significant at 5%
A19: Test 3 - Does a BIGGER rally into the election predict a BIGGER (or smaller) 6-month gain afterward?
A20: Pearson correlation between 'Rally low->election close %' and 'Ret 6m %'. Tests momentum (positive corr) vs mean-reversion (negative corr).
A21: Index | B21: Correlation (r) | C21: Approx. p-value | D21: Interpretation
A22: SPX | B22: =CORREL('Data - SPX'!$E$5:$E$20,'Data - SPX'!$P$5:$P$20) -> 0.17958545 | C22: =TDIST(ABS((B22*SQRT(COUNT('Data - SPX'!$E$5:$E$20)-2))/SQRT(1-B22^2)),COUNT('Data - SPX'!$E$5:$E$20)-2,2) -> 0.50572105 | D22: =IF(AND(B22<-0.3,C22<0.1),"Mean-reverting: a hotter rally into the election tends to borrow from the 6-month move, not add to it",IF(AND(B22>0.3,C22<0.1),"Momentum: a hotter rally into the election tends to continue","No reliable relationship either way")) -> No reliable relationship either way
A23: DJI | B23: =CORREL('Data - DJI'!$E$5:$E$20,'Data - DJI'!$P$5:$P$20) -> -0.71000589 | C23: =TDIST(ABS((B23*SQRT(COUNT('Data - DJI'!$E$5:$E$20)-2))/SQRT(1-B23^2)),COUNT('Data - DJI'!$E$5:$E$20)-2,2) -> 0.0020595931 | D23: =IF(AND(B23<-0.3,C23<0.1),"Mean-reverting: a hotter rally into the election tends to borrow from the 6-month move, not add to it",IF(AND(B23>0.3,C23<0.1),"Momentum: a hotter rally into the election tends to continue","No reliable relationship either way")) -> Mean-reverting: a hotter rally into the election tends to borrow from the 6-month move, not add to it
A24: NASDAQ | B24: =CORREL('Data - NASDAQ'!$E$5:$E$17,'Data - NASDAQ'!$P$5:$P$17) -> -0.55912082 | C24: =TDIST(ABS((B24*SQRT(COUNT('Data - NASDAQ'!$E$5:$E$17)-2))/SQRT(1-B24^2)),COUNT('Data - NASDAQ'!$E$5:$E$17)-2,2) -> 0.046974308 | D24: =IF(AND(B24<-0.3,C24<0.1),"Mean-reverting: a hotter rally into the election tends to borrow from the 6-month move, not add to it",IF(AND(B24>0.3,C24<0.1),"Momentum: a hotter rally into the election tends to continue","No reliable relationship either way")) -> Mean-reverting: a hotter rally into the election tends to borrow from the 6-month move, not add to it
A26: Test 4 - Does a DEEPER post-election shakeout predict a BIGGER rebound? ('the shakeout hypothesis')
A27: Pearson correlation between 'Retest drop from election close %' (more negative = deeper dip) and 'Ret 6m %'. A positive correlation supports 'the sharper the shakeout, the bigger the eventual rally.'
A28: Index | B28: Correlation (r) | C28: Approx. p-value | D28: Interpretation
A29: SPX | B29: =IFERROR(CORREL('Data - SPX'!$I$5:$I$20,'Data - SPX'!$P$5:$P$20),"n/a") -> 0.10965285 | C29: =IFERROR(TDIST(ABS((B29*SQRT(COUNT('Data - SPX'!$I$5:$I$20)-2))/SQRT(1-B29^2)),COUNT('Data - SPX'!$I$5:$I$20)-2,2),"n/a") -> 0.68602524 | D29: =IFERROR(IF(AND(B29>0.3,C29<0.1),"Shakeout hypothesis supported: deeper post-election dips tend to precede bigger 6-month rebounds",IF(AND(B29<-0.3,C29<0.1),"Opposite: deeper dips tend to precede weaker rebounds","No reliable relationship either way")),"n/a") -> No reliable relationship either way
A30: DJI | B30: =IFERROR(CORREL('Data - DJI'!$I$5:$I$20,'Data - DJI'!$P$5:$P$20),"n/a") -> 0.68376216 | C30: =IFERROR(TDIST(ABS((B30*SQRT(COUNT('Data - DJI'!$I$5:$I$20)-2))/SQRT(1-B30^2)),COUNT('Data - DJI'!$I$5:$I$20)-2,2),"n/a") -> 0.0034927529 | D30: =IFERROR(IF(AND(B30>0.3,C30<0.1),"Shakeout hypothesis supported: deeper post-election dips tend to precede bigger 6-month rebounds",IF(AND(B30<-0.3,C30<0.1),"Opposite: deeper dips tend to precede weaker rebounds","No reliable relationship either way")),"n/a") -> Shakeout hypothesis supported: deeper post-election dips tend to precede bigger 6-month rebounds
A31: NASDAQ | B31: =IFERROR(CORREL('Data - NASDAQ'!$I$5:$I$17,'Data - NASDAQ'!$P$5:$P$17),"n/a") -> 0.78965525 | C31: =IFERROR(TDIST(ABS((B31*SQRT(COUNT('Data - NASDAQ'!$I$5:$I$17)-2))/SQRT(1-B31^2)),COUNT('Data - NASDAQ'!$I$5:$I$17)-2,2),"n/a") -> 0.0013238202 | D31: =IFERROR(IF(AND(B31>0.3,C31<0.1),"Shakeout hypothesis supported: deeper post-election dips tend to precede bigger 6-month rebounds",IF(AND(B31<-0.3,C31<0.1),"Opposite: deeper dips tend to precede weaker rebounds","No reliable relationship either way")),"n/a") -> Shakeout hypothesis supported: deeper post-election dips tend to precede bigger 6-month rebounds

Sheet Midterm Cycle Effect
A1: The 'Midterm Effect': Where Midterm Years Rank in the 4-Year Presidential Cycle
A2: Every US year since the early 1960s, grouped by its position in the 4-year presidential cycle (year 2 = midterm, year 3 = pre-election, year 4 = presidential election, year 1 = post-election). Source: user's original study file, 'descriptive only'. Not limited to just the 16-17 midterm events above - uses the full annual return history.
A4: SPX
A5: Cycle Position | B5: n (years) | C5: Mean 1M % | D5: Mean 3M % | E5: Mean 6M % | F5: Mean 12M %
A6: Midterm | B6: 16 | C6: 0.014 | D6: 0.069 | E6: 0.138 | F6: 0.142
A7: Post-election | B7: 17 | C7: 0.009 | D7: 0 | E7: 0.014 | F7: 0
A8: Pre-election | B8: 17 | C8: 0.009 | D8: 0.045 | E8: 0.053 | F8: 0.1
A9: Presidential | B9: 17 | C9: 0.01 | D9: 0.034 | E9: 0.052 | F9: 0.105
A11: DJI
A12: Cycle Position | B12: n (years) | C12: Mean 1M % | D12: Mean 3M % | E12: Mean 6M % | F12: Mean 12M %
A13: Midterm | B13: 20 | C13: 0.002 | D13: 0.147 | E13: 0.142 | F13: 0.15
A14: Post-election | B14: 20 | C14: 0.009 | D14: 0.093 | E14: 0.084 | F14: 0.088
A15: Pre-election | B15: 19 | C15: -0.006 | D15: 0.072 | E15: 0.074 | F15: 0.072
A16: Presidential | B16: 19 | C16: -0.007 | D16: 0.094 | E16: 0.084 | F16: 0.089
A18: NASDAQ
A19: Cycle Position | B19: n (years) | C19: Mean 1M % | D19: Mean 3M % | E19: Mean 6M % | F19: Mean 12M %
A20: Midterm | B20: 14 | C20: 0.011 | D20: 0.152 | E20: 0.143 | F20: 0.154
A21: Post-election | B21: 14 | C21: 0.015 | D21: 0.165 | E21: 0.153 | F21: 0.151
A22: Pre-election | B22: 14 | C22: -0.004 | D22: 0.152 | E22: 0.15 | F22: 0.167
A23: Presidential | B23: 14 | C23: -0.003 | D23: 0.105 | E23: 0.085 | F23: 0.085
A25: Mean 6-Month Return by Cycle Position (chart source)
A26: Cycle Position | B26: SPX | C26: DJI | D26: NASDAQ
A27: Midterm | B27: =F6 -> 0.142 | C27: =F13 -> 0.15 | D27: =F20 -> 0.154
A28: Post-election | B28: =F7 -> 0 | C28: =F14 -> 0.088 | D28: =F21 -> 0.151
A29: Pre-election | B29: =F8 -> 0.1 | C29: =F15 -> 0.072 | D29: =F22 -> 0.167
A30: Presidential | B30: =F9 -> 0.105 | C30: =F16 -> 0.089 | D30: =F23 -> 0.085

Sheet Data - SPX
A1: SPX - Midterm Election Event Table (source data)
A2: Raw, hand-compiled study data (blue = source input). Each row = one US midterm-election cycle. Percent fields are in %.
A4: Year | B4: Election | C4: Pre-low date | D4: Pre-low price | E4: Rally low->elec close % | F4: Peak date | G4: Pullback peak->elec close % | H4: Retest low date | I4: Retest drop from elec close % | J4: Shape | K4: Ret 1d % | L4: Ret 5d % | M4: Ret 10d % | N4: Ret 1m % | O4: Ret 3m % | P4: Ret 6m % | Q4: Ret 12m % | R4: Pre-low -> 6m % | S4: Retest low -> 6m % | T4: 6m worst low vs elec close % | U4: JanFeb low vs elec close %
A5: 1962 | B5: 1962-11-06 | C5: 1962-10-24 | D5: 52.55 | E5: 11.04 | F5: 1962-11-05 | G5: -0.6 | H5: 1962-11-07 | I5: -1.01 | J5: Higher low (no real retest) | K5: 0.62 | L5: 1.9 | M5: 3.6 | N5: 7.85 | O5: 13.8 | P5: 19.16 | Q5: 24.78 | R5: 32.31 | S5: 20.38 | T5: -1.01 | U5: 6.8
A6: 1966 | B6: 1966-11-08 | C6: 1966-10-10 | D6: 72.28 | E6: 11.69 | F6: 1966-11-02 | G6: -1.16 | H6: 1966-11-22 | I6: -2.28 | J6: Higher low (no real retest) | K6: 0.81 | L6: 1.19 | M6: -1.31 | N6: 1.64 | O6: 8.66 | P6: 17.16 | Q6: 12.89 | R6: 30.85 | S6: 19.89 | T6: -2.28 | U6: -1.61
A7: 1970 | B7: 1970-11-03 | C7: 1970-09-24 | D7: 80.82 | E7: 4.21 | F7: 1970-10-06 | G7: -4.02 | H7: 1970-11-19 | I7: -2.36 | J7: N (retest ~ old low) | K7: 0.2 | L7: 0.68 | M7: -0.89 | N7: 5.56 | O7: 14.74 | P7: 22.64 | Q7: 12.69 | R7: 27.8 | S7: 25.61 | T7: -2.36 | U7: 7.62
A8: 1974 | B8: 1974-11-05 | C8: 1974-10-04 | D8: 60.96 | E8: 23.21 | F8: 1974-10-31 | G8: -1.04 | H8: 1974-12-09 | I8: -14.62 | J8: Higher low (no real retest) | K8: -0.48 | L8: -1.92 | M8: -9.2 | N8: -11.96 | O8: 5.11 | P8: 19.93 | Q8: 18.69 | R8: 47.77 | S8: 40.46 | T8: -14.62 | U8: -8.6
A9: 1978 | B9: 1978-11-07 | C9: 1978-10-30 | D9: 91.65 | E9: 2.4 | F9: 1978-11-01 | G9: -3.65 | H9: 1978-11-14 | I9: -2.22 | J9: N (retest ~ old low) | K9: 0.64 | L9: -1.45 | M9: 1.24 | N9: 3.44 | O9: 3.53 | P9: 5.51 | Q9: 6.41 | R9: 8.04 | S9: 7.9 | T9: -2.22 | U9: 1.46
A10: 1982 | B10: 1982-11-02 | C10: 1982-10-26 | D10: 131.5 | E10: 4.56 | F10: 1982-11-02 | G10: -0.74 | H10: 1982-11-25 | I10: -4.43 | J10: N (retest ~ old low) | K10: 3.91 | L10: 4.02 | M10: -1.51 | N10: 0.97 | O10: 4.17 | P10: 17.91 | Q10: 19.89 | R10: 23.28 | S10: 23.37 | T10: -4.43 | U10: 0.43
A11: 1986 | B11: 1986-11-04 | C11: 1986-09-29 | D11: 228.08 | E11: 7.94 | F11: 1986-11-04 | G11: -0.09 | H11: 1986-11-19 | I11: -4.34 | J11: Higher low (no real retest) | K11: 0.15 | L11: 0.36 | M11: -3.83 | N11: 2.78 | O11: 13.58 | P11: 17.53 | Q11: 1.12 | R11: 26.87 | S11: 22.87 | T11: -4.34 | U11: -1.64
A12: 1990 | B12: 1990-11-06 | C12: 1990-10-11 | D12: 294.51 | E12: 5.81 | F12: 1990-10-22 | G12: -1.33 | H12: 1990-11-08 | I12: -2.11 | J12: Higher low (no real retest) | K12: -1.8 | L12: 1.94 | M12: 1.18 | N12: 5.6 | O12: 14.91 | P12: 21.97 | Q12: 25.14 | R12: 29.06 | S12: 24.6 | T12: -2.11 | U12: -0.73
A13: 1994 | B13: 1994-11-08 | C13: 1994-10-05 | D13: 449.27 | E13: 3.65 | F13: 1994-10-31 | G13: -1.91 | H13: 1994-12-09 | I13: -4.89 | J13: N (retest ~ old low) | K13: -0.05 | L13: -0.13 | M13: -3.34 | N13: -4.34 | O13: 3.34 | P13: 12.52 | Q13: 27.07 | R13: 16.62 | S13: 18.31 | T13: -4.89 | U13: -1.81
A14: 1998 | B14: 1998-11-03 | C14: 1998-10-08 | D14: 923.32 | E14: 20.31 | F14: 1998-11-03 | G14: -0.37 | H14: 1998-11-05 | I14: -0.12 | J14: Higher low (no real retest) | K14: 0.7 | L14: 1.57 | M14: 2.56 | N14: 3.54 | O14: 14.51 | P14: 21.95 | Q14: 21.97 | R14: 46.71 | S14: 22.09 | T14: -0.4 | U14: 8.62
A15: 2002 | B15: 2002-11-05 | C15: 2002-10-10 | D15: 768.63 | E15: 19.1 | F15: 2002-11-04 | G15: -0.99 | H15: 2002-12-31 | I15: -5.02 | J15: Higher low (no real retest) | K15: 0.91 | L15: -3.54 | M15: -2.04 | N15: -0.97 | O15: -7.84 | P15: 1.22 | Q15: 14.9 | R15: 20.55 | S15: 6.57 | T15: -13.82 | U15: -11.92
A16: 2006 | B16: 2006-11-07 | C16: 2006-11-03 | D16: 1360.98 | E16: 1.61 | F16: 2006-11-07 | G16: -0.39 | H16: 2006-11-10 | I16: -0.52 | J16: No pre-election rally | K16: 0.21 | L16: 0.75 | M16: 1.44 | N16: 1.77 | O16: 4.86 | P16: 9.16 | Q16: 6.71 | R16: 10.91 | S16: 9.73 | T16: -1.36 | U16: 0.48
... A20: 2022 | B20: 2022-11-08 | C20: 2022-10-13 | D20: 3491.58 | E20: 9.64 | F20: 2022-11-01 | G20: -2.14 | H20: 2022-11-09 | I20: -2.19 | J20: Higher low (no real retest) | K20: -2.08 | L20: 4.27 | M20: 4.58 | N20: 3.54 | O20: 7.57 | P20: 8.1 | Q20: 14.49 | R20: 18.52 | S20: 10.52 | T20: -2.19 | U20: -0.88

Sheet Data - DJI
A1: DJI - Midterm Election Event Table (source data)
A2: Raw, hand-compiled study data (blue = source input). Each row = one US midterm-election cycle. Percent fields are in %.
A4: Year | B4: Election | C4: Pre-low date | D4: Pre-low price | E4: Rally low->elec close % | F4: Peak date | G4: Pullback peak->elec close % | H4: Retest low date | I4: Retest drop from elec close % | J4: Shape | K4: Ret 1d % | L4: Ret 5d % | M4: Ret 10d % | N4: Ret 1m % | O4: Ret 3m % | P4: Ret 6m % | Q4: Ret 12m % | R4: Pre-low -> 6m % | S4: Retest low -> 6m % | T4: 6m worst low vs elec close % | U4: JanFeb low vs elec close %
A5: 1962 | B5: 1962-11-06 | C5: 1962-10-24 | D5: 549.65 | E5: 8.28 | F5: 1962-11-01 | G5: -16.54 | H5: 1962-12-06 | I5: -2.53 | J5: Higher low (no real retest) | K5: -1.03 | L5: 4.69 | M5: 6.35 | N5: -2.39 | O5: 21.16 | P5: 21.97 | Q5: 20.7 | R5: 32.07 | S5: 25.14 | T5: -2.53 | U5: 8.13
A6: 1966 | B6: 1966-11-08 | C6: 1966-10-10 | D6: 735.74 | E6: 13.89 | F6: 1966-11-02 | G6: -16.04 | H6: 1966-11-10 | I6: -10.2 | J6: N (retest ~ old low) | K6: -9.46 | L6: -2.03 | M6: -4.9 | N6: 0.31 | O6: 10.07 | P6: 3.23 | Q6: 9.87 | R6: 17.56 | S6: 14.95 | T6: -10.2 | U6: -2
A7: 1970 | B7: 1970-11-03 | C7: 1970-09-24 | D7: 749.04 | E7: 3.88 | F7: 1970-10-12 | G7: -5.65 | H7: 1970-12-06 | I7: -13.27 | J7: N (retest makes lower low) | K7: -8.75 | L7: 0.18 | M7: -3.07 | N7: -0.21 | O7: 13.48 | P7: 15.41 | Q7: 15.59 | R7: 19.89 | S7: 33.06 | T7: -13.27 | U7: 4.7
A8: 1974 | B8: 1974-11-05 | C8: 1974-10-04 | D8: 840.27 | E8: 0.54 | F8: 1974-11-03 | G8: -5.43 | H8: 1974-12-17 | I8: -31.06 | J8: No pre-election rally | K8: 0.86 | L8: -20.38 | M8: -26.03 | N8: 5.01 | O8: 0.43 | P8: 1.28 | Q8: -6.55 | R8: 1.82 | S8: 46.9 | T8: -31.06 | U8: -26.71
A9: 1978 | B9: 1978-11-07 | C9: 1978-10-30 | D9: 782.05 | E9: 5.02 | F9: 1978-11-05 | G9: -1.68 | H9: 1978-12-04 | I9: -6.97 | J9: N (retest ~ old low) | K9: 8.47 | L9: -3.57 | M9: -1.91 | N9: 0.44 | O9: 1.55 | P9: 1.76 | Q9: 2.75 | R9: 6.87 | S9: 9.39 | T9: -6.97 | U9: -2.77
A10: 1982 | B10: 1982-11-02 | C10: 1982-10-26 | D10: 979.76 | E10: -14.81 | F10: 1982-10-27 | G10: -17.65 | H10: 1982-11-08 | I10: -7.49 | J10: No pre-election rally | K10: -3.49 | L10: 21.34 | M10: 23.65 | N10: -0.1 | O10: 27.31 | P10: 25.18 | Q10: 30.17 | R10: 6.65 | S10: 35.32 | T10: -7.49 | U10: 22.23
A11: 1986 | B11: 1986-11-04 | C11: 1986-09-29 | D11: 1733 | E11: 3.3 | F11: 1986-10-12 | G11: -7.87 | H11: 1986-12-02 | I11: -9.52 | J11: N (retest makes lower low) | K11: 3.12 | L11: 5.91 | M11: 1.51 | N11: -2.5 | O11: 29.62 | P11: 27.16 | Q11: 26.75 | R11: 31.36 | S11: 40.53 | T11: -9.52 | U11: 1.96
A12: 1990 | B12: 1990-11-06 | C12: 1990-10-12 | D12: 2566.5 | E12: 12.7 | F12: 1990-11-06 | G12: -0.32 | H12: 1990-11-10 | I12: -18.95 | J12: N (retest makes lower low) | K12: 1.39 | L12: -12.35 | M12: -12.53 | N12: 1.41 | O12: 1.59 | P12: 3.9 | Q12: 3.23 | R12: 17.1 | S12: 28.2 | T12: -18.95 | U12: -15.36
A13: 1994 | B13: 1994-11-08 | C13: 1994-10-05 | D13: 3628.45 | E13: 3.37 | F13: 1994-10-19 | G13: -5.03 | H13: 1994-12-05 | I13: -3.25 | J13: N (retest ~ old low) | K13: 3.36 | L13: 2.51 | M13: -2.03 | N13: 0.47 | O13: 25.04 | P13: 23.04 | Q13: 23.13 | R13: 27.19 | S13: 27.17 | T13: -3.25 | U13: 1.16
A14: 1998 | B14: 1998-11-03 | C14: 1998-10-09 | D14: 7519.5 | E14: 15.38 | F14: 1998-10-12 | G14: -3.74 | H14: 1998-12-01 | I14: -14.8 | J14: N (retest ~ old low) | K14: 4.79 | L14: 1.71 | M14: 4.2 | N14: -0.19 | O14: 7.17 | P14: 12.22 | Q14: 14.08 | R14: 29.48 | S14: 31.72 | T14: -14.8 | U14: 4.47
A15: 2002 | B15: 2002-11-05 | C15: 2002-10-10 | D15: 7197.49 | E15: 41.38 | F15: 2002-11-03 | G15: -4.42 | H15: 2002-11-10 | I15: -25.9 | J15: Higher low (no real retest) | K15: -6.47 | L15: -17.86 | M15: -16.6 | N15: 0.14 | O15: -15.66 | P15: -16.16 | Q15: -19.39 | R15: 18.54 | S15: 13.14 | T15: -25.9 | U15: -25.03
A16: 2006 | B16: 2006-11-07 | C16: 2006-11-04 | D16: 11053.17 | E16: 0.74 | F16: 2006-11-05 | G16: -4.34 | H16: 2006-12-06 | I16: -3.09 | J16: No pre-election rally | K16: -0.42 | L16: 8.95 | M16: 10.61 | N16: -1.09 | O16: 21.56 | P16: 21.83 | Q16: 21.94 | R16: 22.73 | S16: 25.72 | T16: -3.09 | U16: 8.31
... A20: 2022 | B20: 2022-11-08 | C20: 2022-10-13 | D20: 28660.94 | E20: 16.31 | F20: 2022-11-01 | G20: -8.09 | H20: 2022-11-10 | I20: -12.79 | J20: N (retest ~ old low) | K20: -12.29 | L20: 0.65 | M20: 2.57 | N20: 1.27 | O20: 5.84 | P20: 2.86 | Q20: 5.83 | R20: 19.64 | S20: 17.93 | T20: -12.79 | U20: -2.51
A21: 2026 | B21: 2026-11-03 | C21: 2026-10-23 | D21: 52060.21 | E21: -8.92 | F21: 2026-10-23 | G21: -10.03 | K21: 4.83 | L21: 4.58 | M21: 13.41 | N21: -1.56

Sheet Data - NASDAQ
A1: NASDAQ - Midterm Election Event Table (source data)
A2: Raw, hand-compiled study data (blue = source input). Each row = one US midterm-election cycle. Percent fields are in %.
A4: Year | B4: Election | C4: Pre-low date | D4: Pre-low price | E4: Rally low->elec close % | F4: Peak date | G4: Pullback peak->elec close % | H4: Retest low date | I4: Retest drop from elec close % | J4: Shape | K4: Ret 1d % | L4: Ret 5d % | M4: Ret 10d % | N4: Ret 1m % | O4: Ret 3m % | P4: Ret 6m % | Q4: Ret 12m % | R4: Pre-low -> 6m % | S4: Retest low -> 6m % | T4: 6m worst low vs elec close % | U4: JanFeb low vs elec close %
A5: 1974 | B5: 1974-11-05 | C5: 1974-10-04 | D5: 89.87 | E5: -0.09 | F5: 1974-11-03 | G5: -6.33 | H5: 1974-12-09 | I5: -35.73 | J5: No pre-election rally | K5: -7.18 | L5: -25.69 | M5: -30.85 | N5: 6.69 | O5: -10.62 | P5: -9.63 | Q5: -15.01 | R5: -9.71 | S5: 40.6 | T5: -35.73 | U5: -32.4
A6: 1978 | B6: 1978-11-07 | C6: 1978-10-30 | D6: 112.4 | E6: 6.61 | F6: 1978-11-07 | G6: 0 | H6: 1978-12-01 | I6: -16.93 | J6: N (retest makes lower low) | K6: 10.16 | L6: -5.7 | M6: -4.44 | N6: 0.38 | O6: 14.35 | P6: 14.99 | Q6: 15.87 | R6: 22.59 | S6: 38.43 | T6: -16.93 | U6: -1.66
A7: 1982 | B7: 1982-11-02 | C7: 1982-10-26 | D7: 209.92 | E7: -13.18 | F7: 1982-10-29 | G7: -14.29 | H7: 1982-12-08 | I7: -12.3 | J7: No pre-election rally | K7: -6.67 | L7: 11.01 | M7: 25.81 | N7: 0.15 | O7: 36.23 | P7: 27.7 | Q7: 40.82 | R7: 10.87 | S7: 45.6 | T7: -12.3 | U7: 29.89
A8: 1986 | B8: 1986-11-04 | C8: 1986-09-29 | D8: 347.1 | E8: 9.16 | F8: 1986-10-06 | G8: -4.03 | H8: 1986-12-02 | I8: -8.97 | J8: N (retest ~ old low) | K8: 4.35 | L8: -4.65 | M8: -6.94 | N8: -2.43 | O8: 14.04 | P8: 13.22 | Q8: 13.86 | R8: 23.6 | S8: 24.38 | T8: -22.96 | U8: -19.71
A9: 1990 | B9: 1990-11-06 | C9: 1990-10-12 | D9: 369.8 | E9: 25.15 | F9: 1990-11-06 | G9: 0 | H9: 1990-12-10 | I9: -30.21 | J9: N (retest makes lower low) | K9: 0.24 | L9: -23.75 | M9: -24.74 | N9: 0.82 | O9: 6.11 | P9: 9.16 | Q9: 7.3 | R9: 36.61 | S9: 56.41 | T9: -30.21 | U9: -23.73
A10: 1994 | B10: 1994-11-08 | C10: 1994-10-05 | D10: 724.1 | E10: 0.57 | F10: 1994-11-03 | G10: -7.79 | H10: 1994-12-07 | I10: -3.39 | J10: No pre-election rally | K10: 5.14 | L10: 5.69 | M10: 1.17 | N10: 0.47 | O10: 35.1 | P10: 29.33 | Q10: 37.89 | R10: 30.06 | S10: 33.87 | T10: -3.39 | U10: 3.13
A11: 1998 | B11: 1998-11-03 | C11: 1998-09-10 | D11: 1419.11 | E11: 23.8 | F11: 1998-10-12 | G11: -14.65 | H11: 1998-12-01 | I11: -16.58 | J11: Higher low (no real retest) | K11: 5.19 | L11: 6 | M11: 7.96 | N11: 0.41 | O11: 28.58 | P11: 33.03 | Q11: 37.31 | R11: 64.69 | S11: 59.46 | T11: -16.58 | U11: 25.55
A12: 2002 | B12: 2002-11-05 | C12: 2002-10-10 | D12: 1108.49 | E12: 55.64 | F12: 2002-11-01 | G12: -16.2 | H12: 2002-11-10 | I12: -31.61 | J12: Higher low (no real retest) | K12: -13.22 | L12: -23.54 | M12: -19.22 | N12: 1.79 | O12: -12.89 | P12: -12.82 | Q12: -21.24 | R12: 35.68 | S12: 27.47 | T12: -31.61 | U12: -26.86
A13: 2006 | B13: 2006-11-07 | C13: 2006-11-04 | D13: 2302.19 | E13: -7.53 | F13: 2006-11-04 | G13: -9.01 | H13: 2006-11-08 | I13: -3.71 | J13: No pre-election rally | K13: -3.34 | L13: 13.04 | M13: 15.21 | N13: -1.81 | O13: 23.65 | P13: 24.79 | Q13: 24.56 | R13: 15.4 | S13: 29.6 | T13: -3.71 | U13: 10.83
A14: 2010 | B14: 2010-11-02 | C14: 2010-10-19 | D14: 2422.14 | E14: -10.1 | F14: 2010-10-29 | G14: -13.51 | H14: 2010-12-02 | I14: -1.17 | J14: No pre-election rally | K14: 8.77 | L14: 10.33 | M14: 15.48 | N14: 0.28 | O14: 26.28 | P14: 24.1 | Q14: 29.03 | R14: 11.56 | S14: 25.57 | T14: -1.99 | U14: 13.41
A15: 2014 | B15: 2014-11-04 | C15: 2014-10-21 | D15: 4356.1 | E15: -8.18 | F15: 2014-10-31 | G15: -13.83 | H15: 2014-12-05 | I15: 2.31 | J15: No pre-election rally | K15: 8.31 | L15: 16.52 | M15: 17.57 | N15: 8.09 | O15: 22.18 | P15: 24.58 | Q15: 21.26 | R15: 14.39 | S15: 21.77 | T15: -0.2 | U15: 13.82
A16: 2018 | B16: 2018-11-06 | C16: 2018-10-29 | D16: 6922.83 | E16: 10.65 | F16: 2018-11-06 | G16: -0.23 | H16: 2018-12-24 | I16: -19.19 | J16: N (retest makes lower low) | K16: 0.74 | L16: -5.99 | M16: -9.81 | N16: 0.57 | O16: 4.92 | P16: -1.1 | Q16: 2.12 | R16: 9.43 | S16: 22.38 | T16: -19.19 | U16: -15.05
A17: 2022 | B17: 2022-11-08 | C17: 2022-10-13 | D17: 10088.83 | E17: 26.67 | F17: 2022-11-01 | G17: -15.69 | H17: 2022-12-28 | I17: -20.13 | J17: N (retest ~ old low) | K17: -18.42 | L17: -12.49 | M17: -11.69 | N17: 2.09 | O17: 9.34 | P17: 7.92 | Q17: 6.77 | R17: 36.7 | S17: 35.11 | T17: -20.13 | U17: -15.46
A18: 2026 | B18: 2026-11-03 | C18: 2026-10-23 | D18: 25866.15 | E18: -12.18 | F18: 2026-10-27 | G18: -14.41 | K18: 15.66 | L18: 4.48 | M18: 17.05 | N18: -1.78

Sheet Data - Avg Path
A1: Average Price Path by Trading Day vs Election (index rebased to 100 at election close)
A2: Mean of all completed midterm cycles per index. Trading day 0 = election-day close. Source: user's event tables.
A4: Trading day vs election | B4: S&P 500 (SPX) | C4: Dow (DJI) | D4: Nasdaq (NDQ)
A5: -30 | B5: 96.83 | C5: 97.63 | D5: 96.5
A6: -29 | B6: 97.19 | C6: 97.48 | D6: 96.7
A7: -28 | B7: 96.42 | C7: 97.32 | D7: 96.45
A8: -27 | B8: 96.31 | C8: 98.76 | D8: 98.31
A9: -26 | B9: 96.54 | C9: 98.62 | D9: 97.86
A10: -25 | B10: 96.65 | C10: 100.22 | D10: 102.7
A11: -24 | B11: 96.34 | C11: 101.2 | D11: 100.41
A12: -23 | B12: 95.84 | C12: 101.54 | D12: 99.65
A13: -22 | B13: 95.85 | C13: 100.54 | D13: 100.23
A14: -21 | B14: 96.02 | C14: 98.29 | D14: 98.75
A15: -20 | B15: 96.12 | C15: 98.28 | D15: 97.48
A16: -19 | B16: 96.26 | C16: 96.84 | D16: 94.91
... A165: 130 | B165: 113.61 | C165: 113.37 | D165: 116.53
